brutx4/FTP.py
brutx4/Zip.py
brutx4/__init__.py
brutx4/hash.py
brutx4-1.1.dist-info/METADATA
brutx4-1.1.dist-info/WHEEL
brutx4-1.1.dist-info/top_level.txt
brutx4-1.1.dist-info/RECORD
