Metadata-Version: 2.1
Name: brutx4
Version: 1.1
Summary: A Bruteforce Package by Python
Home-page: UNKNOWN
Author: Rakib Hossain
Author-email: rakib4ggp@gmail.com
License: UNKNOWN
Platform: UNKNOWN
Classifier: Programming Language :: Python :: 3
Classifier: License :: OSI Approved :: MIT License
Classifier: Operating System :: OS Independent
